[
  {
    "date": "",
    "word": "PIANO",
    "hint": "Whispers born of ivory’s touch"
  },
  {
    "date": "",
    "word": "RIVER",
    "hint": "Serpent weaving through earth’s veins"
  },
  {
    "date": "",
    "word": "BREAD",
    "hint": "Hearth’s gift from golden dust"
  },
  {
    "date": "",
    "word": "TIGER",
    "hint": "Shadowed stripes in jungle’s heart"
  },
  {
    "date": "",
    "word": "CLOUD",
    "hint": "Drifter cloaking heaven’s face"
  },
  {
    "date": "",
    "word": "APPLE",
    "hint": "Orchard’s gem or forbidden bite"
  },
  {
    "date": "",
    "word": "CHAIR",
    "hint": "Throne for a moment’s pause"
  },
  {
    "date": "",
    "word": "HOUSE",
    "hint": "Walls cradling lives’ quiet tales"
  },
  {
    "date": "",
    "word": "CLOCK",
    "hint": "Time’s pulse in endless rounds"
  },
  {
    "date": "",
    "word": "TRAIN",
    "hint": "Iron beast on fated paths"
  },
  {
    "date": "",
    "word": "BEACH",
    "hint": "Edge where tides kiss fleeting grains"
  },
  {
    "date": "",
    "word": "HORSE",
    "hint": "Spirit galloping through open winds"
  },
  {
    "date": "",
    "word": "MOUSE",
    "hint": "Furtive shadow in silent corners"
  },
  {
    "date": "",
    "word": "PLANT",
    "hint": "Life reaching for sun’s soft glow"
  },
  {
    "date": "",
    "word": "STONE",
    "hint": "Earth’s ancient whisper, cold and still"
  },
  {
    "date": "",
    "word": "BLADE",
    "hint": "Gleam that severs with quiet will"
  },
  {
    "date": "",
    "word": "WATER",
    "hint": "Essence flowing in life’s deep stream"
  },
  {
    "date": "",
    "word": "CROWN",
    "hint": "Circlet perched on glory’s crest"
  },
  {
    "date": "",
    "word": "LIGHT",
    "hint": "Glow piercing the shadowed veil"
  },
  {
    "date": "",
    "word": "SHEEP",
    "hint": "Soft wanderers of pastoral dreams"
  },
  {
    "date": "",
    "word": "LEMON",
    "hint": "Tart spark from sunlit boughs"
  },
  {
    "date": "",
    "word": "DREAM",
    "hint": "Mist spun in slumber’s silent realm"
  },
  {
    "date": "",
    "word": "BRUSH",
    "hint": "Stroke that shapes or sweeps away"
  },
  {
    "date": "",
    "word": "TABLE",
    "hint": "Plane holding life’s fleeting feasts"
  },
  {
    "date": "",
    "word": "SMILE",
    "hint": "Curve blooming in joy’s soft light"
  },
  {
    "date": "",
    "word": "GRAPE",
    "hint": "Jewel ripened on tangled vines"
  },
  {
    "date": "",
    "word": "WHALE",
    "hint": "Titan roaming the ocean’s pulse"
  },
  {
    "date": "",
    "word": "MUSIC",
    "hint": "Harmony drifting through fleeting air"
  },
  {
    "date": "",
    "word": "SUGAR",
    "hint": "Sweet whisper from distant stalks"
  },
  {
    "date": "",
    "word": "SHORE",
    "hint": "Threshold where waves murmur secrets"
  },
  {
    "date": "",
    "word": "ORBIT",
    "hint": "Dance around a cosmic flame"
  },
  {
    "date": "",
    "word": "PIXEL",
    "hint": "Spark weaving a digital dream"
  },
  {
    "date": "",
    "word": "FROST",
    "hint": "Winter’s breath on dawn’s frail edge"
  },
  {
    "date": "",
    "word": "PILOT",
    "hint": "Guide soaring through boundless skies"
  },
  {
    "date": "",
    "word": "UNITY",
    "hint": "Bond woven in shared silences"
  },
  {
    "date": "",
    "word": "QUEST",
    "hint": "Path chasing an elusive star"
  },
  {
    "date": "",
    "word": "FLAME",
    "hint": "Flicker born of restless embers"
  },
  {
    "date": "",
    "word": "WINDY",
    "hint": "Murmur stirring the unseen air"
  },
  {
    "date": "",
    "word": "GRASS",
    "hint": "Soft veil beneath wandering skies"
  },
  {
    "date": "",
    "word": "OCEAN",
    "hint": "Vast heart of untamed depths"
  },
  {
    "date": "",
    "word": "GHOST",
    "hint": "Echo adrift beyond the veil"
  },
  {
    "date": "",
    "word": "SPARK",
    "hint": "Brief gleam of hidden fires"
  },
  {
    "date": "",
    "word": "CROWD",
    "hint": "Tide of voices in fleeting union"
  },
  {
    "date": "",
    "word": "SWORD",
    "hint": "Edge forged for ancient oaths"
  },
  {
    "date": "",
    "word": "FAITH",
    "hint": "Anchor cast in unseen hopes"
  },
  {
    "date": "",
    "word": "TOWER",
    "hint": "Spire piercing the heavens’ veil"
  },
  {
    "date": "",
    "word": "FLOOR",
    "hint": "Steadfast stage for life’s dance"
  },
  {
    "date": "",
    "word": "BLOOM",
    "hint": "Brief sigh of nature’s artistry"
  },
  {
    "date": "",
    "word": "TRUTH",
    "hint": "Glimmer obscured by shadowed thoughts"
  },
  {
    "date": "",
    "word": "GLASS",
    "hint": "Fragile mirror of fleeting light"
  },
  {
    "date": "",
    "word": "SHADE",
    "hint": "Soft refuge from relentless glow"
  },
  {
    "date": "",
    "word": "MONEY",
    "hint": "Glimmer fueling mortal desires"
  },
  {
    "date": "",
    "word": "STARS",
    "hint": "Distant embers in night’s embrace"
  },
  {
    "date": "",
    "word": "FIELD",
    "hint": "Canvas stretched beneath open skies"
  },
  {
    "date": "",
    "word": "WATCH",
    "hint": "Guardian of time’s silent flow"
  },
  {
    "date": "",
    "word": "RIDGE",
    "hint": "Spine rising from earth’s quiet bones"
  },
  {
    "date": "",
    "word": "FLOCK",
    "hint": "Chorus of wings in fleeting harmony"
  },
  {
    "date": "",
    "word": "GLOVE",
    "hint": "Sheath for hands in winter’s grasp"
  },
  {
    "date": "",
    "word": "PEARL",
    "hint": "Gem born of ocean’s hidden tears"
  },
  {
    "date": "",
    "word": "VISTA",
    "hint": "Gaze upon earth’s boundless dreams"
  },
  {
    "date": "",
    "word": "SKULL",
    "hint": "Relic guarding life’s faded echo"
  },
  {
    "date": "",
    "word": "FENCE",
    "hint": "Boundary woven of wood or will"
  },
  {
    "date": "",
    "word": "NIGHT",
    "hint": "Cloak draped over weary days"
  },
  {
    "date": "",
    "word": "FROTH",
    "hint": "Foam dancing on restless tides"
  },
  {
    "date": "",
    "word": "SNAKE",
    "hint": "Slithering shadow of silent wilds"
  },
  {
    "date": "",
    "word": "CLIFF",
    "hint": "Edge staring into abyss’ call"
  },
  {
    "date": "",
    "word": "CHARM",
    "hint": "Whisper that sways the heart’s tide"
  },
  {
    "date": "",
    "word": "STORM",
    "hint": "Fury dancing in darkened skies"
  },
  {
    "date": "",
    "word": "FIBER",
    "hint": "Thread binding life’s unseen weave"
  },
  {
    "date": "",
    "word": "HONEY",
    "hint": "Nectar stolen from floral hearts"
  },
  {
    "date": "",
    "word": "FLUTE",
    "hint": "Breath shaped into fleeting songs"
  },
  {
    "date": "",
    "word": "SKIRT",
    "hint": "Fabric flowing with graceful steps"
  },
  {
    "date": "",
    "word": "TORCH",
    "hint": "Beacon piercing the shadowed veil"
  },
  {
    "date": "",
    "word": "WHEEL",
    "hint": "Cycle turning through time’s embrace"
  },
  {
    "date": "",
    "word": "BLOOD",
    "hint": "Crimson tide of life’s quiet pulse"
  },
  {
    "date": "",
    "word": "GRAIN",
    "hint": "Seed of earth’s patient labor"
  },
  {
    "date": "",
    "word": "SPICE",
    "hint": "Essence teasing the tongue’s memory"
  },
  {
    "date": "",
    "word": "EAGLE",
    "hint": "Sovereign soaring on wind’s command"
  },
  {
    "date": "",
    "word": "VOICE",
    "hint": "Echo of the soul’s hidden song"
  },
  {
    "date": "",
    "word": "SLOPE",
    "hint": "Earth’s tilt toward unseen horizons"
  },
  {
    "date": "",
    "word": "WINGS",
    "hint": "Sails lifting through boundless air"
  },
  {
    "date": "",
    "word": "PAINT",
    "hint": "Hues dancing on a silent canvas"
  },
  {
    "date": "",
    "word": "SPINE",
    "hint": "Pillar upholding life’s quiet frame"
  },
  {
    "date": "",
    "word": "CREST",
    "hint": "Peak crowned by fleeting winds"
  },
  {
    "date": "",
    "word": "LATCH",
    "hint": "Guardian of doors’ silent trust"
  },
  {
    "date": "",
    "word": "FLAIR",
    "hint": "Spark of style in fleeting acts"
  },
  {
    "date": "",
    "word": "CHEST",
    "hint": "Vessel holding breath and treasure"
  },
  {
    "date": "",
    "word": "MAPLE",
    "hint": "Tree whispering of autumn’s glow"
  },
  {
    "date": "",
    "word": "QUILT",
    "hint": "Patchwork of warmth and memory"
  },
  {
    "date": "",
    "word": "SOUND",
    "hint": "Ripple stirring the silent air"
  },
  {
    "date": "",
    "word": "KNEEL",
    "hint": "Gesture bowing to sacred moments"
  },
  {
    "date": "",
    "word": "SWAMP",
    "hint": "Mire cradling life’s hidden pulse"
  },
  {
    "date": "",
    "word": "BRICK",
    "hint": "Block forged in fire’s embrace"
  },
  {
    "date": "",
    "word": "FABLE",
    "hint": "Tale spun from wisdom’s thread"
  },
  {
    "date": "",
    "word": "GLOOM",
    "hint": "Shadow cast by light’s retreat"
  },
  {
    "date": "",
    "word": "SCENT",
    "hint": "Whisper carried on fleeting breezes"
  },
  {
    "date": "",
    "word": "TULIP",
    "hint": "Petal cradling spring’s soft promise"
  },
  {
    "date": "",
    "word": "VAULT",
    "hint": "Chamber guarding secrets or stars"
  },
  {
    "date": "",
    "word": "CRANE",
    "hint": "Graceful arc in sky or steel"
  },
  {
    "date": "",
    "word": "SPOOL",
    "hint": "Core winding threads of craft"
  },
  {
    "date": "",
    "word": "GLINT",
    "hint": "Fleeting shimmer in twilight’s gaze"
  },
  {
    "date": "",
    "word": "MOUND",
    "hint": "Earth’s gentle rise from silent depths"
  },
  {
    "date": "",
    "word": "SPRAY",
    "hint": "Mist born of restless waters"
  },
  {
    "date": "",
    "word": "VOWEL",
    "hint": "Breath shaping the tongue’s song"
  },
  {
    "date": "",
    "word": "CORAL",
    "hint": "Sculpture grown in ocean’s quiet"
  },
  {
    "date": "",
    "word": "FLEET",
    "hint": "Swift tide of roaming spirits"
  },
  {
    "date": "",
    "word": "CABLE",
    "hint": "Thread binding distant voices"
  },
  {
    "date": "",
    "word": "HEDGE",
    "hint": "Living wall of whispered boundaries"
  },
  {
    "date": "",
    "word": "TRAIL",
    "hint": "Path etched by wandering feet"
  },
  {
    "date": "",
    "word": "RHYME",
    "hint": "Echo binding words in dance"
  },
  {
    "date": "",
    "word": "GROVE",
    "hint": "Sanctuary of whispering boughs"
  },
  {
    "date": "",
    "word": "SHAFT",
    "hint": "Ray or rod piercing the void"
  },
  {
    "date": "",
    "word": "CHILL",
    "hint": "Breath of winter’s fleeting touch"
  },
  {
    "date": "",
    "word": "WRECK",
    "hint": "Relic of journeys lost to time"
  },
  {
    "date": "",
    "word": "FLOOD",
    "hint": "Tide swallowing earth’s quiet voice"
  },
  {
    "date": "",
    "word": "BUDDY",
    "hint": "Shadow sharing life’s fleeting path"
  },
  {
    "date": "",
    "word": "LAYER",
    "hint": "Veil stacked in silent folds"
  },
  {
    "date": "",
    "word": "SCARF",
    "hint": "Cloth dancing with winter’s breath"
  },
  {
    "date": "",
    "word": "GLIDE",
    "hint": "Grace flowing on unseen currents"
  },
  {
    "date": "",
    "word": "BUNCH",
    "hint": "Cluster bound by nature’s hand"
  },
  {
    "date": "",
    "word": "PLUME",
    "hint": "Feather drifting on wind’s soft call"
  },
  {
    "date": "",
    "word": "FORGE",
    "hint": "Hearth shaping metal’s hidden fire"
  },
  {
    "date": "",
    "word": "TWIST",
    "hint": "Turn bending fate’s quiet thread"
  },
  {
    "date": "",
    "word": "BERRY",
    "hint": "Jewel ripened in summer’s embrace"
  },
  {
    "date": "",
    "word": "STEAM",
    "hint": "Vapor rising from warmth’s soft breath"
  },
  {
    "date": "",
    "word": "FLARE",
    "hint": "Burst piercing the shadowed night"
  },
  {
    "date": "",
    "word": "KNOTS",
    "hint": "Tangles binding life’s loose ends"
  },
  {
    "date": "",
    "word": "HAZEL",
    "hint": "Shade glowing in autumn’s quiet eyes"
  },
  {
    "date": "",
    "word": "SWEET",
    "hint": "Taste lingering on memory’s tongue"
  },
  {
    "date": "",
    "word": "GLORY",
    "hint": "Radiance crowning fleeting triumphs"
  },
  {
    "date": "",
    "word": "RUSTY",
    "hint": "Mark of time on forgotten iron"
  },
  {
    "date": "",
    "word": "BLAZE",
    "hint": "Fire dancing in untamed glow"
  },
  {
    "date": "",
    "word": "VAPOR",
    "hint": "Mist drifting in warmth’s faint clasp"
  },
  {
    "date": "",
    "word": "CLEFT",
    "hint": "Chasm carved in earth’s old heart"
  },
  {
    "date": "",
    "word": "WOVEN",
    "hint": "Threads entwined in silent craft"
  },
  {
    "date": "",
    "word": "NEXUS",
    "hint": "Core linking paths unseen"
  },
  {
    "date": "",
    "word": "AMBER",
    "hint": "Golden relic of ancient sap"
  },
  {
    "date": "",
    "word": "BAYOU",
    "hint": "Slow waters in tangled green"
  },
  {
    "date": "",
    "word": "SLATE",
    "hint": "Gray tablet of ancient stone"
  },
  {
    "date": "",
    "word": "GLEAM",
    "hint": "Soft flash in twilight’s hush"
  },
  {
    "date": "",
    "word": "HATCH",
    "hint": "Door to secrets yet unseen"
  },
  {
    "date": "",
    "word": "GULLY",
    "hint": "Scar etched by water’s fleeting rush"
  },
  {
    "date": "",
    "word": "NOBLE",
    "hint": "Spirit clad in honor’s grace"
  },
  {
    "date": "",
    "word": "WEDGE",
    "hint": "Force that splits with quiet might"
  },
  {
    "date": "",
    "word": "CRUSH",
    "hint": "Weight that breaks in silent press"
  },
  {
    "date": "",
    "word": "BROOK",
    "hint": "Gentle stream in wooded shade"
  },
  {
    "date": "",
    "word": "GLADE",
    "hint": "Open heart in forest’s embrace"
  },
  {
    "date": "",
    "word": "SHAWL",
    "hint": "Drape warming shoulders in dusk"
  },
  {
    "date": "",
    "word": "TREAD",
    "hint": "Steps marking earth’s soft skin"
  },
  {
    "date": "",
    "word": "SPURT",
    "hint": "Sudden rush from hidden springs"
  },
  {
    "date": "",
    "word": "HAVEN",
    "hint": "Refuge cradling weary souls"
  },
  {
    "date": "",
    "word": "FLUSH",
    "hint": "Rush of warmth or flowing tide"
  }
]
